alda/__init__.py
alda/bencode.py
alda/client.py
alda/nrepl.py
alda_python-0.1.0.dist-info/LICENSE
alda_python-0.1.0.dist-info/METADATA
alda_python-0.1.0.dist-info/WHEEL
alda_python-0.1.0.dist-info/top_level.txt
alda_python-0.1.0.dist-info/RECORD
