Metadata-Version: 2.1
Name: alda-python
Version: 0.1.0
Summary: Python client for Alda (https://alda.io/)
Home-page: https://github.com/nvitucci/alda-python
Author: Nicola Vitucci
Author-email: nicola.vitucci@gmail.com
Project-URL: Bug Tracker, https://github.com/nvitucci/alda-python/issues
Project-URL: Source, https://github.com/nvitucci/alda-python
Classifier: Development Status :: 3 - Alpha
Classifier: Intended Audience :: Developers
Classifier: License :: OSI Approved :: Eclipse Public License 2.0 (EPL-2.0)
Classifier: Operating System :: OS Independent
Classifier: Programming Language :: Python :: 3
Classifier: Programming Language :: Python :: 3 :: Only
Classifier: Topic :: Artistic Software
Classifier: Topic :: Multimedia :: Sound/Audio
Classifier: Topic :: Software Development :: Libraries :: Python Modules
Classifier: Typing :: Typed
Requires-Python: >=3.8
License-File: LICENSE
Provides-Extra: dev
Requires-Dist: black ; extra == 'dev'
Requires-Dist: isort ; extra == 'dev'
Requires-Dist: mypy ; extra == 'dev'
Requires-Dist: pytest ; extra == 'dev'
Requires-Dist: tox ; extra == 'dev'
